metrixpp/__init__.py
metrixpp/metrixpp.py
metrixpp/ext/__init__.py
metrixpp/ext/std/__init__.py
metrixpp/ext/std/suppress.ini
metrixpp/ext/std/suppress.py
metrixpp/ext/std/code/__init__.py
metrixpp/ext/std/code/complexity.ini
metrixpp/ext/std/code/complexity.py
metrixpp/ext/std/code/cpp.ini
metrixpp/ext/std/code/cpp.py
metrixpp/ext/std/code/cs.ini
metrixpp/ext/std/code/cs.py
metrixpp/ext/std/code/debug.ini
metrixpp/ext/std/code/debug.py
metrixpp/ext/std/code/filelines.ini
metrixpp/ext/std/code/filelines.py
metrixpp/ext/std/code/java.ini
metrixpp/ext/std/code/java.py
metrixpp/ext/std/code/length.ini
metrixpp/ext/std/code/length.py
metrixpp/ext/std/code/lines.ini
metrixpp/ext/std/code/lines.py
metrixpp/ext/std/code/longlines.ini
metrixpp/ext/std/code/longlines.py
metrixpp/ext/std/code/magic.ini
metrixpp/ext/std/code/magic.py
metrixpp/ext/std/code/member.ini
metrixpp/ext/std/code/member.py
metrixpp/ext/std/code/mi.ini
metrixpp/ext/std/code/mi.py
metrixpp/ext/std/code/ratio.ini
metrixpp/ext/std/code/ratio.py
metrixpp/ext/std/code/test.ini
metrixpp/ext/std/code/test.py
metrixpp/ext/std/code/todo.ini
metrixpp/ext/std/code/todo.py
metrixpp/ext/std/tools/__init__.py
metrixpp/ext/std/tools/collect.ini
metrixpp/ext/std/tools/collect.py
metrixpp/ext/std/tools/export.ini
metrixpp/ext/std/tools/export.py
metrixpp/ext/std/tools/info.ini
metrixpp/ext/std/tools/info.py
metrixpp/ext/std/tools/limit.ini
metrixpp/ext/std/tools/limit.py
metrixpp/ext/std/tools/limit_backend.ini
metrixpp/ext/std/tools/limit_backend.py
metrixpp/ext/std/tools/report.ini
metrixpp/ext/std/tools/report.py
metrixpp/ext/std/tools/view.ini
metrixpp/ext/std/tools/view.py
metrixpp/mpp/__init__.py
metrixpp/mpp/api.py
metrixpp/mpp/cout.py
metrixpp/mpp/dbf.ini
metrixpp/mpp/dbf.py
metrixpp/mpp/log.ini
metrixpp/mpp/log.py
metrixpp/mpp/promout.py
metrixpp/mpp/utils.py
metrixpp/mpp/internal/__init__.py
metrixpp/mpp/internal/api_impl.py
metrixpp/mpp/internal/dbwrap.py
metrixpp/mpp/internal/loader.py
metrixpp-1.8.1.dist-info/LICENSE
metrixpp-1.8.1.dist-info/METADATA
metrixpp-1.8.1.dist-info/WHEEL
metrixpp-1.8.1.dist-info/entry_points.txt
metrixpp-1.8.1.dist-info/top_level.txt
metrixpp-1.8.1.dist-info/RECORD
