Metadata-Version: 2.1
Name: metrixpp
Version: 1.8.1
Summary: Metrix++ is an extendable tool for code metrics collection and analysis.
Home-page: https://github.com/metrixplusplus/metrixplusplus
Author: Stefan Strobel
Author-email: stefan.strobel@shimatta.net
Project-URL: Documentation, https://metrixplusplus.github.io/
Project-URL: Source, https://github.com/metrixplusplus/metrixplusplus
Project-URL: Tracker, https://github.com/metrixplusplus/metrixplusplus/issues
Classifier: Programming Language :: Python :: 3
Classifier: License :: OSI Approved :: MIT License
Classifier: Operating System :: OS Independent
Requires-Python: >=3.7
License-File: LICENSE
Requires-Dist: pytablewriter
